CHANGES.rst
LICENSE.txt
README.rst
setup.py
setuptools_subversion.py
setuptools_subversion.egg-info/PKG-INFO
setuptools_subversion.egg-info/SOURCES.txt
setuptools_subversion.egg-info/dependency_links.txt
setuptools_subversion.egg-info/entry_points.txt
setuptools_subversion.egg-info/top_level.txt
setuptools_subversion.egg-info/zip-safe