Metadata-Version: 1.0
Name: setuptools-subversion
Version: 2.0
Summary: Setuptools revision control system plugin for Subversion
Home-page: http://pypi.python.org/pypi/setuptools_subversion
Author: Martijn Pieters
Author-email: mj@zopatista.com
License: BSD
Platform: UNKNOWN
Classifier: Development Status :: 5 - Production/Stable
Classifier: Environment :: Plugins
Classifier: Framework :: Setuptools Plugin
Classifier: Intended Audience :: Developers
Classifier: License :: OSI Approved :: BSD License
Classifier: Programming Language :: Python :: 2.4
Classifier: Programming Language :: Python :: 2.5
Classifier: Programming Language :: Python :: 2.6
Classifier: Programming Language :: Python :: 2.7
Classifier: Programming Language :: Python :: 3
Classifier: Topic :: Software Development :: Version Control
